CHANGES.rst
CONTRIBUTORS.rst
DEVELOP.rst
LICENSE.rst
MANIFEST.in
README.rst
setup.cfg
setup.py
docs/conf.py
docs/index.rst
src/collective/__init__.py
src/collective.defaultexcludedfromnav.egg-info/PKG-INFO
src/collective.defaultexcludedfromnav.egg-info/SOURCES.txt
src/collective.defaultexcludedfromnav.egg-info/dependency_links.txt
src/collective.defaultexcludedfromnav.egg-info/entry_points.txt
src/collective.defaultexcludedfromnav.egg-info/namespace_packages.txt
src/collective.defaultexcludedfromnav.egg-info/not-zip-safe
src/collective.defaultexcludedfromnav.egg-info/requires.txt
src/collective.defaultexcludedfromnav.egg-info/top_level.txt
src/collective/defaultexcludedfromnav/__init__.py
src/collective/defaultexcludedfromnav/configure.zcml
src/collective/defaultexcludedfromnav/interfaces.py
src/collective/defaultexcludedfromnav/permissions.zcml
src/collective/defaultexcludedfromnav/setuphandlers.py
src/collective/defaultexcludedfromnav/testing.py
src/collective/defaultexcludedfromnav/upgrades.py
src/collective/defaultexcludedfromnav/upgrades.zcml
src/collective/defaultexcludedfromnav/browser/__init__.py
src/collective/defaultexcludedfromnav/browser/adapters.py
src/collective/defaultexcludedfromnav/browser/configure.zcml
src/collective/defaultexcludedfromnav/browser/controlpanel.py
src/collective/defaultexcludedfromnav/browser/overrides/.gitkeep
src/collective/defaultexcludedfromnav/browser/static/.gitkeep
src/collective/defaultexcludedfromnav/locales/README.rst
src/collective/defaultexcludedfromnav/locales/__init__.py
src/collective/defaultexcludedfromnav/locales/collective.defaultexcludedfromnav.pot
src/collective/defaultexcludedfromnav/locales/update.py
src/collective/defaultexcludedfromnav/locales/update.sh
src/collective/defaultexcludedfromnav/locales/en/LC_MESSAGES/collective.defaultexcludedfromnav.po
src/collective/defaultexcludedfromnav/locales/fr/LC_MESSAGES/collective.defaultexcludedfromnav.po
src/collective/defaultexcludedfromnav/profiles/default/browserlayer.xml
src/collective/defaultexcludedfromnav/profiles/default/catalog.xml
src/collective/defaultexcludedfromnav/profiles/default/controlpanel.xml
src/collective/defaultexcludedfromnav/profiles/default/metadata.xml
src/collective/defaultexcludedfromnav/profiles/default/registry.xml
src/collective/defaultexcludedfromnav/profiles/default/rolemap.xml
src/collective/defaultexcludedfromnav/profiles/uninstall/browserlayer.xml
src/collective/defaultexcludedfromnav/tests/__init__.py
